[
  {
    "_id": "634b07e016a6192280521116",
    "index": 0,
    "guid": "2dd7c7fc-eb62-4e50-a1e9-43bac0fcf6f9",
    "isActive": false,
    "balance": "$3,861.33",
    "picture": "http://placehold.it/32x32",
    "age": 30,
    "eyeColor": "blue",
    "name": "Tami Kelly",
    "gender": "female",
    "company": "HALAP",
    "email": "tamikelly@halap.com",
    "phone": "+1 (972) 402-2372",
    "address": "466 Waldorf Court, Fairmount, Oregon, 4018",
    "about": "Et magna pariatur id sint dolor aute laborum consectetur consectetur labore laborum commodo ipsum. Irure qui commodo sint velit quis do consectetur aliquip consequat proident consectetur cupidatat. Ipsum consequat voluptate ut aliquip. Aliqua aliqua deserunt est reprehenderit ullamco sunt labore sint veniam et nostrud eu Lorem laboris. Sit ad ut et in excepteur nisi excepteur. Occaecat proident nisi aliqua duis amet occaecat excepteur qui amet labore esse. Amet laborum proident quis id et.\r\n",
    "registered": "2017-08-31T09:49:10 -09:00",
    "latitude": -69.702372,
    "longitude": 33.752228,
    "tags": [
      "cillum",
      "proident",
      "quis",
      "quis",
      "enim",
      "commodo",
      "esse"
    ],
    "friends": [
      {
        "id": 0,
        "name": "Mullen Cote"
      },
      {
        "id": 1,
        "name": "Teri Knowles"
      },
      {
        "id": 2,
        "name": "Cecilia Avila"
      }
    ],
    "greeting": "Hello, Tami Kelly! You have 3 unread messages.",
    "favoriteFruit": "banana"
  },
  {
    "_id": "634b07e0fbf16e81ad45a21f",
    "index": 1,
    "guid": "e480890a-6301-4cc5-a28e-eac7af555986",
    "isActive": true,
    "balance": "$3,316.40",
    "picture": "http://placehold.it/32x32",
    "age": 24,
    "eyeColor": "green",
    "name": "Johnson Hawkins",
    "gender": "male",
    "company": "RUBADUB",
    "email": "johnsonhawkins@rubadub.com",
    "phone": "+1 (932) 554-3776",
    "address": "182 Chester Street, Corinne, West Virginia, 8540",
    "about": "Elit dolor deserunt minim minim ipsum laboris eu. Tempor veniam sit nisi ea ipsum culpa laborum cillum occaecat laborum ut. Consectetur nulla proident laborum et elit cillum culpa officia aliquip. Exercitation nulla incididunt velit nisi do aute. Pariatur non ullamco ullamco laboris sunt tempor est laborum eu occaecat.\r\n",
    "registered": "2022-05-14T01:22:07 -09:00",
    "latitude": -69.867076,
    "longitude": 157.309928,
    "tags": [
      "ad",
      "fugiat",
      "veniam",
      "commodo",
      "est",
      "esse",
      "ullamco"
    ],
    "friends": [
      {
        "id": 0,
        "name": "Mckenzie Roberson"
      },
      {
        "id": 1,
        "name": "Bailey Conner"
      },
      {
        "id": 2,
        "name": "Ortega Sanchez"
      }
    ],
    "greeting": "Hello, Johnson Hawkins! You have 7 unread messages.",
    "favoriteFruit": "banana"
  },
  {
    "_id": "634b07e021f99a502c820c7a",
    "index": 2,
    "guid": "5992010f-0909-4fb7-a00e-8fa2a42aaa2e",
    "isActive": false,
    "balance": "$3,986.12",
    "picture": "http://placehold.it/32x32",
    "age": 39,
    "eyeColor": "brown",
    "name": "Staci Barlow",
    "gender": "female",
    "company": "FLUM",
    "email": "stacibarlow@flum.com",
    "phone": "+1 (869) 480-2803",
    "address": "892 Roebling Street, Barstow, Utah, 6789",
    "about": "Et proident amet exercitation officia irure anim proident nulla proident eiusmod. Laborum ullamco nisi pariatur exercitation sunt. Nostrud nulla culpa excepteur consectetur labore. Consequat commodo non est tempor duis. Ad id laboris quis pariatur cillum.\r\n",
    "registered": "2021-06-24T10:06:41 -09:00",
    "latitude": 39.723011,
    "longitude": 175.308049,
    "tags": [
      "enim",
      "in",
      "do",
      "non",
      "sunt",
      "id",
      "anim"
    ],
    "friends": [
      {
        "id": 0,
        "name": "Woods Young"
      },
      {
        "id": 1,
        "name": "Randi Mullen"
      },
      {
        "id": 2,
        "name": "Hyde Hooper"
      }
    ],
    "greeting": "Hello, Staci Barlow! You have 7 unread messages.",
    "favoriteFruit": "apple"
  },
  {
    "_id": "634b07e02cc3395613e3f315",
    "index": 3,
    "guid": "a9949f06-3455-4fe0-aa9f-13c2a0e6a541",
    "isActive": true,
    "balance": "$2,132.27",
    "picture": "http://placehold.it/32x32",
    "age": 36,
    "eyeColor": "brown",
    "name": "Eunice Copeland",
    "gender": "female",
    "company": "TWIIST",
    "email": "eunicecopeland@twiist.com",
    "phone": "+1 (839) 580-2746",
    "address": "977 Garden Place, Wanship, Michigan, 8516",
    "about": "Tempor ipsum nisi adipisicing culpa proident culpa excepteur tempor ex. Elit ad eiusmod cupidatat nostrud occaecat excepteur culpa. Aute veniam ut duis enim consequat laboris magna. Enim proident aliqua ut veniam proident id excepteur.\r\n",
    "registered": "2014-07-27T10:15:59 -09:00",
    "latitude": 41.341934,
    "longitude": -1.758636,
    "tags": [
      "laboris",
      "exercitation",
      "elit",
      "officia",
      "consequat",
      "mollit",
      "quis"
    ],
    "friends": [
      {
        "id": 0,
        "name": "Bright Melton"
      },
      {
        "id": 1,
        "name": "Alice Mcbride"
      },
      {
        "id": 2,
        "name": "Sophie Curry"
      }
    ],
    "greeting": "Hello, Eunice Copeland! You have 5 unread messages.",
    "favoriteFruit": "banana"
  },
  {
    "_id": "634b07e0b9776af06653fe6a",
    "index": 4,
    "guid": "e2af57f3-4360-4fa6-9d7e-9ae2add60a9d",
    "isActive": false,
    "balance": "$1,263.11",
    "picture": "http://placehold.it/32x32",
    "age": 38,
    "eyeColor": "green",
    "name": "Hansen Holland",
    "gender": "male",
    "company": "SILODYNE",
    "email": "hansenholland@silodyne.com",
    "phone": "+1 (863) 402-2750",
    "address": "741 Cooke Court, Castleton, Colorado, 1236",
    "about": "Dolore excepteur mollit et ipsum laborum cupidatat culpa aliquip laboris amet voluptate. Commodo aliqua esse proident eiusmod amet fugiat labore enim. Sunt ut amet dolor exercitation Lorem pariatur nostrud excepteur culpa duis sit ex. Nostrud Lorem laboris Lorem sint mollit est veniam officia enim sunt et dolor veniam. Veniam sint sint proident occaecat qui ut ex eiusmod pariatur exercitation cillum quis.\r\n",
    "registered": "2020-07-07T02:17:27 -09:00",
    "latitude": -71.860363,
    "longitude": 142.033707,
    "tags": [
      "voluptate",
      "ea",
      "dolore",
      "qui",
      "elit",
      "ea",
      "laboris"
    ],
    "friends": [
      {
        "id": 0,
        "name": "Ball Hensley"
      },
      {
        "id": 1,
        "name": "Farmer Cox"
      },
      {
        "id": 2,
        "name": "Hallie Sexton"
      }
    ],
    "greeting": "Hello, Hansen Holland! You have 8 unread messages.",
    "favoriteFruit": "strawberry"
  },
  {
    "_id": "634b07e02acbb297e9b10de0",
    "index": 5,
    "guid": "84d31f8b-7d76-4172-85f0-e2d4cfa8cba6",
    "isActive": false,
    "balance": "$2,045.90",
    "picture": "http://placehold.it/32x32",
    "age": 32,
    "eyeColor": "brown",
    "name": "Avila Hewitt",
    "gender": "male",
    "company": "ASSITIA",
    "email": "avilahewitt@assitia.com",
    "phone": "+1 (865) 541-3596",
    "address": "464 Greenwood Avenue, Cressey, Palau, 9958",
    "about": "Consequat eiusmod est commodo labore officia. Exercitation deserunt culpa exercitation deserunt amet aute incididunt laborum aute proident sit. Ipsum aliqua nulla sit laborum consequat.\r\n",
    "registered": "2016-08-28T06:38:33 -09:00",
    "latitude": -51.247717,
    "longitude": -72.912089,
    "tags": [
      "in",
      "incididunt",
      "do",
      "veniam",
      "cillum",
      "nostrud",
      "eu"
    ],
    "friends": [
      {
        "id": 0,
        "name": "Gaines Newton"
      },
      {
        "id": 1,
        "name": "Mejia Morton"
      },
      {
        "id": 2,
        "name": "Young Joseph"
      }
    ],
    "greeting": "Hello, Avila Hewitt! You have 6 unread messages.",
    "favoriteFruit": "apple"
  },
  {
    "_id": "634b07e08a0770c6b526a5b2",
    "index": 6,
    "guid": "77bae993-1f58-445f-b6e8-59445f5d87e0",
    "isActive": false,
    "balance": "$2,961.86",
    "picture": "http://placehold.it/32x32",
    "age": 39,
    "eyeColor": "green",
    "name": "Marquita Barry",
    "gender": "female",
    "company": "VIOCULAR",
    "email": "marquitabarry@viocular.com",
    "phone": "+1 (858) 448-2794",
    "address": "125 Dorset Street, Kimmell, Indiana, 7130",
    "about": "Officia tempor velit amet nulla ipsum minim esse eiusmod reprehenderit cillum consequat. Occaecat aliquip cupidatat dolor irure officia cillum deserunt deserunt commodo est non. Dolore mollit elit anim et eu non minim. Sunt dolor tempor qui in cillum eiusmod magna cupidatat minim dolor commodo nulla do commodo. Cillum voluptate excepteur consequat id fugiat laborum nostrud aute incididunt deserunt amet sunt adipisicing aliqua. Cillum et eiusmod dolore eu anim Lorem nisi in labore veniam adipisicing veniam. Ut Lorem Lorem veniam incididunt exercitation irure anim tempor amet exercitation officia minim nulla.\r\n",
    "registered": "2021-06-12T06:40:29 -09:00",
    "latitude": 46.701049,
    "longitude": 21.722613,
    "tags": [
      "excepteur",
      "Lorem",
      "aliquip",
      "ut",
      "eu",
      "laboris",
      "cupidatat"
    ],
    "friends": [
      {
        "id": 0,
        "name": "Lily Pruitt"
      },
      {
        "id": 1,
        "name": "Weeks Schmidt"
      },
      {
        "id": 2,
        "name": "Laverne Richardson"
      }
    ],
    "greeting": "Hello, Marquita Barry! You have 1 unread messages.",
    "favoriteFruit": "banana"
  },
  {
    "_id": "634b07e07a413c13331ed4fc",
    "index": 7,
    "guid": "b1fd7b4a-ea79-460e-ac90-824e4db788c6",
    "isActive": false,
    "balance": "$1,777.52",
    "picture": "http://placehold.it/32x32",
    "age": 29,
    "eyeColor": "blue",
    "name": "Merrill Vargas",
    "gender": "male",
    "company": "PHOLIO",
    "email": "merrillvargas@pholio.com",
    "phone": "+1 (819) 554-2390",
    "address": "530 Rock Street, Zarephath, Hawaii, 5977",
    "about": "Culpa id magna laboris dolor sint nisi ipsum deserunt tempor nulla non. Pariatur laboris velit officia est esse enim fugiat ex Lorem et occaecat. Aliquip Lorem sit cillum sint nostrud irure irure do ullamco sunt eu excepteur. Eiusmod ullamco do elit nisi consequat sint veniam dolore excepteur eu fugiat ipsum. Culpa adipisicing sint ut eiusmod anim dolor ad. Qui aliquip et amet ipsum. Ipsum ut consequat laboris enim aliquip mollit exercitation.\r\n",
    "registered": "2020-03-25T08:18:09 -09:00",
    "latitude": -83.810004,
    "longitude": -118.575716,
    "tags": [
      "dolore",
      "aliquip",
      "est",
      "sit",
      "enim",
      "id",
      "nulla"
    ],
    "friends": [
      {
        "id": 0,
        "name": "Angelica Sharp"
      },
      {
        "id": 1,
        "name": "Rivera Dalton"
      },
      {
        "id": 2,
        "name": "Madelyn Browning"
      }
    ],
    "greeting": "Hello, Merrill Vargas! You have 5 unread messages.",
    "favoriteFruit": "apple"
  }
]